mmCV/__init__.py
mmCV/version.py
lykmmcv-0.5.6.dist-info/METADATA
lykmmcv-0.5.6.dist-info/WHEEL
lykmmcv-0.5.6.dist-info/top_level.txt
lykmmcv-0.5.6.dist-info/RECORD
