Metadata-Version: 2.1
Name: lykmmcv
Version: 0.5.6
Summary: from mmcv 0.5.6
Home-page: UNKNOWN
Author: liuyuankai
Author-email: 2452378121@qq.com
License: UNKNOWN
Platform: UNKNOWN
